pypasstray.py
setup.py
pypasstray.egg-info/PKG-INFO
pypasstray.egg-info/SOURCES.txt
pypasstray.egg-info/dependency_links.txt
pypasstray.egg-info/top_level.txt