Metadata-Version: 1.0
Name: pypasstray
Version: 0.1
Summary: A simple GTK3 system tray indicator for the UNIX password manager (pass)
Home-page: https://github.com/ozans/pypasstray
Author: Ozan Safi
Author-email: ozansafi@gmail.com
License: UNKNOWN
Platform: UNKNOWN
